setup.py
micropython_redis.egg-info/PKG-INFO
micropython_redis.egg-info/SOURCES.txt
micropython_redis.egg-info/dependency_links.txt
micropython_redis.egg-info/requires.txt
micropython_redis.egg-info/top_level.txt
micropython_redis.egg-info/zip-safe
uredis/__init__.py
uredis/uredis.py